[
  {
    "0": "Consolidated Statements of Income",
    "1": "",
    "2": "",
    "3": "",
    "4": "",
    "5": "",
    "6": ""
  },
  {
    "0": "Years Ended (In Millions, Except Per Share Amounts)",
    "1": "",
    "2": "Dec 30, 2023",
    "3": "",
    "4": "Dec 31, 2022",
    "5": "",
    "6": "Dec 25, 2021"
  },
  {
    "0": "Net revenue",
    "1": "$",
    "2": "54,228",
    "3": "$",
    "4": "63,054",
    "5": "$",
    "6": "79,024"
  },
  {
    "0": "Cost of sales",
    "1": "",
    "2": "32,517",
    "3": "",
    "4": "36,188",
    "5": "",
    "6": "35,209"
  },
  {
    "0": "Gross margin",
    "1": "",
    "2": "21,711",
    "3": "",
    "4": "26,866",
    "5": "",
    "6": "43,815"
  },
  {
    "0": "Research and development",
    "1": "",
    "2": "16,046",
    "3": "",
    "4": "17,528",
    "5": "",
    "6": "15,190"
  },
  {
    "0": "Marketing, general, and administrative",
    "1": "",
    "2": "5,634",
    "3": "",
    "4": "7,002",
    "5": "",
    "6": "6,543"
  },
  {
    "0": "Restructuring and other charges",
    "1": "",
    "2": "(62)",
    "3": "",
    "4": "2",
    "5": "",
    "6": "2,626"
  },
  {
    "0": "Operating expenses",
    "1": "",
    "2": "21,618",
    "3": "",
    "4": "24,532",
    "5": "",
    "6": "24,359"
  },
  {
    "0": "Operating income",
    "1": "",
    "2": "93",
    "3": "",
    "4": "2,334",
    "5": "",
    "6": "19,456"
  },
  {
    "0": "Gains (losses) on equity investments, net",
    "1": "",
    "2": "40",
    "3": "",
    "4": "4,268",
    "5": "",
    "6": "2,729"
  },
  {
    "0": "Interest and other, net",
    "1": "",
    "2": "629",
    "3": "",
    "4": "1,166",
    "5": "",
    "6": "(482)"
  },
  {
    "0": "Income before taxes",
    "1": "",
    "2": "762",
    "3": "",
    "4": "7,768",
    "5": "",
    "6": "21,703"
  },
  {
    "0": "Provision for (benefit from) taxes",
    "1": "",
    "2": "(913)",
    "3": "",
    "4": "(249)",
    "5": "",
    "6": "1,835"
  },
  {
    "0": "Net income",
    "1": "",
    "2": "1,675",
    "3": "",
    "4": "8,017",
    "5": "",
    "6": "19,868"
  },
  {
    "0": "Less: Net income (loss) attributable to non-controlling interests",
    "1": "",
    "2": "(14)",
    "3": "",
    "4": "3",
    "5": "",
    "6": "\u2014"
  },
  {
    "0": "Net income attributable to Intel",
    "1": "$",
    "2": "1,689",
    "3": "$",
    "4": "8,014",
    "5": "$",
    "6": "19,868"
  },
  {
    "0": "Earnings per share attributable to Intel\u2014basic",
    "1": "$",
    "2": "0.40",
    "3": "$",
    "4": "1.95",
    "5": "$",
    "6": "4.89"
  },
  {
    "0": "Earnings per share attributable to Intel\u2014diluted",
    "1": "$",
    "2": "0.40",
    "3": "$",
    "4": "1.94",
    "5": "$",
    "6": "4.86"
  },
  {
    "0": "Weighted average shares of common stock outstanding:",
    "1": "",
    "2": "",
    "3": "",
    "4": "",
    "5": "",
    "6": ""
  },
  {
    "0": "Basic",
    "1": "",
    "2": "4,190",
    "3": "",
    "4": "4,108",
    "5": "",
    "6": "4,059"
  },
  {
    "0": "Diluted",
    "1": "",
    "2": "4,212",
    "3": "",
    "4": "4,123",
    "5": "",
    "6": "4,090"
  }
]