[
  {
    "0": "",
    "1": "",
    "2": "February 10, 2023, between Intel Corporation and",
    "3": "",
    "4": "",
    "5": "",
    "6": ""
  },
  {
    "0": "",
    "1": "",
    "2": "Computershare Trust Company, National Association (as",
    "3": "",
    "4": "",
    "5": "",
    "6": ""
  },
  {
    "0": "",
    "1": "",
    "2": "successor to Wells Fargo Bank, National Association), as",
    "3": "",
    "4": "",
    "5": "",
    "6": ""
  },
  {
    "0": "",
    "1": "",
    "2": "trustee",
    "3": "",
    "4": "",
    "5": "",
    "6": ""
  },
  {
    "0": "4.19",
    "1": "",
    "2": "Description of Intel Securities Registered under Section",
    "3": "10-K",
    "4": "000-06217",
    "5": "4.18",
    "6": "1/27/2022"
  },
  {
    "0": "",
    "1": "",
    "2": "12 of the Exchange Act",
    "3": "",
    "4": "",
    "5": "",
    "6": ""
  },
  {
    "0": "\u2020",
    "1": "",
    "2": "",
    "3": "",
    "4": "",
    "5": "",
    "6": ""
  },
  {
    "0": "10.1",
    "1": "",
    "2": "Intel Corporation 2006 Equity Incentive Plan, as",
    "3": "S-8",
    "4": "000-06217",
    "5": "99.1",
    "6": "9/26/2023"
  },
  {
    "0": "",
    "1": "",
    "2": "amended and restated, effective May 11, 2023",
    "3": "",
    "4": "",
    "5": "",
    "6": ""
  },
  {
    "0": "",
    "1": "\u2020",
    "2": "",
    "3": "",
    "4": "",
    "5": "",
    "6": ""
  },
  {
    "0": "10.1.2",
    "1": "",
    "2": "Intel Corporation Form of Notice of Grant - Restricted",
    "3": "10-Q",
    "4": "000-06217",
    "5": "10.1",
    "6": "10/25/2018"
  },
  {
    "0": "",
    "1": "",
    "2": "Stock Units",
    "3": "",
    "4": "",
    "5": "",
    "6": ""
  },
  {
    "0": "",
    "1": "\u2020",
    "2": "",
    "3": "",
    "4": "",
    "5": "",
    "6": ""
  },
  {
    "0": "10.1.3",
    "1": "",
    "2": "Intel Corporation Form of Restricted Stock Unit Grant",
    "3": "10-Q",
    "4": "000-06217",
    "5": "10.3",
    "6": "4/26/2019"
  },
  {
    "0": "",
    "1": "",
    "2": "Agreement under the 2006 Equity Incentive Plan (for",
    "3": "",
    "4": "",
    "5": "",
    "6": ""
  },
  {
    "0": "",
    "1": "",
    "2": "RSUs with retirement vesting terms granted to",
    "3": "",
    "4": "",
    "5": "",
    "6": ""
  },
  {
    "0": "",
    "1": "",
    "2": "executives on or after January 30, 2019)",
    "3": "",
    "4": "",
    "5": "",
    "6": ""
  },
  {
    "0": "",
    "1": "\u2020",
    "2": "",
    "3": "",
    "4": "",
    "5": "",
    "6": ""
  },
  {
    "0": "10.1.4",
    "1": "",
    "2": "Intel Corporation Form of Restricted Stock Unit Grant",
    "3": "10-Q",
    "4": "000-06217",
    "5": "10.4",
    "6": "4/26/2019"
  },
  {
    "0": "",
    "1": "",
    "2": "Agreement under the 2006 Equity Incentive Plan (for",
    "3": "",
    "4": "",
    "5": "",
    "6": ""
  },
  {
    "0": "",
    "1": "",
    "2": "RSUs without retirement vesting terms granted to",
    "3": "",
    "4": "",
    "5": "",
    "6": ""
  },
  {
    "0": "",
    "1": "",
    "2": "executives on or after January 30, 2019)",
    "3": "",
    "4": "",
    "5": "",
    "6": ""
  },
  {
    "0": "",
    "1": "\u2020",
    "2": "",
    "3": "",
    "4": "",
    "5": "",
    "6": ""
  },
  {
    "0": "10.1.5",
    "1": "",
    "2": "Intel Corporation Form of Restricted Stock Unit Grant",
    "3": "10-Q",
    "4": "000-06217",
    "5": "10.5",
    "6": "4/26/2019"
  },
  {
    "0": "",
    "1": "",
    "2": "Agreement under the 2006 Equity Incentive Plan (for",
    "3": "",
    "4": "",
    "5": "",
    "6": ""
  },
  {
    "0": "",
    "1": "",
    "2": "performance-based RSUs granted to grandfathered",
    "3": "",
    "4": "",
    "5": "",
    "6": ""
  },
  {
    "0": "",
    "1": "",
    "2": "executives on or after January 30, 2019)",
    "3": "",
    "4": "",
    "5": "",
    "6": ""
  },
  {
    "0": "",
    "1": "\u2020",
    "2": "",
    "3": "",
    "4": "",
    "5": "",
    "6": ""
  },
  {
    "0": "10.1.6",
    "1": "",
    "2": "Intel Corporation Form of Restricted Stock Unit Grant",
    "3": "10-Q",
    "4": "000-06217",
    "5": "10.1",
    "6": "4/24/2020"
  },
  {
    "0": "",
    "1": "",
    "2": "Agreement under the 2006 Equity Incentive Plan (for",
    "3": "",
    "4": "",
    "5": "",
    "6": ""
  },
  {
    "0": "",
    "1": "",
    "2": "performance-based RSUs granted to non-grandfathered",
    "3": "",
    "4": "",
    "5": "",
    "6": ""
  },
  {
    "0": "",
    "1": "",
    "2": "executives on or after January 30, 2019)",
    "3": "",
    "4": "",
    "5": "",
    "6": ""
  },
  {
    "0": "",
    "1": "\u2020",
    "2": "",
    "3": "",
    "4": "",
    "5": "",
    "6": ""
  },
  {
    "0": "10.1.7",
    "1": "",
    "2": "Intel Corporation Form of Restricted Stock Unit Grant",
    "3": "10-Q",
    "4": "000-06217",
    "5": "10.6",
    "6": "4/26/2019"
  },
  {
    "0": "",
    "1": "",
    "2": "Agreement under the 2006 Equity Incentive Plan (for",
    "3": "",
    "4": "",
    "5": "",
    "6": ""
  }
]